{"publicApplicationId":"net.wackware.mylo","description":"MyLo which is short for 'My Location' is a great App that let's you send quick texts or emails that include your location. What's really cool is that your location is encoded with a link to Google Maps\u00ae so the recipient can click the link and see where you are, or get directions to come meet you. MyLo is simple to set up, simple to use. \n\nSo say you have a flat tire on the freeway and want to call you're friend to come get you.\nWhat if you can't see a street sign to tell them where you are? Just use MyLo and they are able to get directions right to you. What if it's an emergency? MyLo can send your location to a single or multiple email or text addresses.\n\nIf you leave the MyLo App open or in card mode, the location windows will continue to update so you can just click 'Send' again to send an update of your location.","version":"1.0.1","versionNote":"1. Fixed bug in app catalog redirect.","homeURL":"http:\/\/www.wackware.net","supportURL":"http:\/\/www.wackware.net","custsupportemail":"dev1@wackware.net","custsupportphonenum":"9165728772","copyright":"Copyright 2011 WackWare","licenseURL":"","locale":"en_US","appSize":751992,"installSize":1310720,"isEncrypted":false,"adultRating":false,"islocationbased":false,"lastModifiedTime":"2012-06-02T07:15:05.000+0000","mediaLink":null,"mediaIcon":null,"attributes":{"provides":{"noApp":false,"dockMode":false,"universalSearch":false,"connectors":["null"],"services":[],"optimizedUserExperience":true}},"price":0.99,"currency":"USD","isAdvertized":false,"filename":"net.wackware.mylo_1.0.1_all.ipk","free":false,"touchpad_exclusive":true,"images":{"1":{"screenshot":"net.wackware.mylo\/1.0.1\/en\/images\/1\/L\/tb_mylo_tp_1.png","thumbnail":"net.wackware.mylo\/1.0.1\/en\/images\/1\/S\/tb_mylo_tp_1.png","orientation":"P","device":"P"},"2":{"screenshot":"net.wackware.mylo\/1.0.1\/en\/images\/2\/L\/tb_mylo_tp_2.png","thumbnail":"net.wackware.mylo\/1.0.1\/en\/images\/2\/S\/tb_mylo_tp_2.png","orientation":"P","device":"P"},"3":{"screenshot":"net.wackware.mylo\/1.0.1\/en\/images\/3\/L\/tb_mylo_tp_3.png","thumbnail":"net.wackware.mylo\/1.0.1\/en\/images\/3\/S\/tb_mylo_tp_3.png","orientation":"P","device":"P"},"4":{"screenshot":"net.wackware.mylo\/1.0.1\/en\/images\/4\/L\/tb_mylo_tp_4.png","thumbnail":"net.wackware.mylo\/1.0.1\/en\/images\/4\/S\/tb_mylo_tp_4.png","orientation":"P","device":"P"},"5":{"screenshot":"net.wackware.mylo\/1.0.1\/en\/images\/5\/L\/ph_mylo_pre3_5.png","thumbnail":"net.wackware.mylo\/1.0.1\/en\/images\/5\/S\/ph_mylo_pre3_5.png","orientation":"P","device":"P"}}}