{"publicApplicationId":"com.rockus.sketchflierhd","description":"Those airplane sketches you drew in class instead of paying attention have come alive. Fly your plane, shoot targets, collect gold, and buy bigger guns. What's that? You drew unicorns dancing on rainbows in your notebook? Well, unicorns aren't real.","version":"1.2.0","versionNote":"","homeURL":"http:\/\/www.rockus-studios.com","supportURL":"http:\/\/rockus-studios.com","custsupportemail":"support@rockus-studios.com","custsupportphonenum":"","copyright":"Copyright 2012 Rockus Studios, LLC","licenseURL":"","locale":"en_US","appSize":6311256,"installSize":6782976,"isEncrypted":false,"adultRating":false,"islocationbased":false,"lastModifiedTime":"2012-06-02T09:07:22.000+0000","mediaLink":null,"mediaIcon":null,"attributes":{"provides":{"noApp":false,"dockMode":false,"universalSearch":false,"connectors":["null"],"services":[],"optimizedUserExperience":true}},"price":1.99,"currency":"USD","isAdvertized":false,"filename":"com.rockus.sketchflierhd_1.2.0_all.ipk","free":false,"touchpad_exclusive":true,"images":{"1":{"screenshot":"com.rockus.sketchflierhd\/1.2.0\/en\/images\/1\/L\/tb_screenshot1.png","thumbnail":"com.rockus.sketchflierhd\/1.2.0\/en\/images\/1\/S\/tb_screenshot1.png","orientation":"L","device":"T"},"2":{"screenshot":"com.rockus.sketchflierhd\/1.2.0\/en\/images\/2\/L\/tb_screenshot2.png","thumbnail":"com.rockus.sketchflierhd\/1.2.0\/en\/images\/2\/S\/tb_screenshot2.png","orientation":"L","device":"T"},"3":{"screenshot":"com.rockus.sketchflierhd\/1.2.0\/en\/images\/3\/L\/tb_screenshot3.png","thumbnail":"com.rockus.sketchflierhd\/1.2.0\/en\/images\/3\/S\/tb_screenshot3.png","orientation":"L","device":"T"}}}