{"publicApplicationId":"com.doublesix.app.babe","description":"A groovy space based arena brawler where the titular heroine must survive an endless army of killer robots. With an arsenal of weapons at her disposal, the robots don't stand a chance!","version":"1.0.1","versionNote":"","homeURL":"http:\/\/www.doublesixgames.com","supportURL":"http:\/\/www.doublesixgames.com","custsupportemail":"","custsupportphonenum":"","copyright":"doublesix video games ltd \u00a9 2009-2010","licenseURL":"","locale":"en_US","appSize":52649934,"installSize":109969408,"isEncrypted":false,"adultRating":false,"islocationbased":false,"lastModifiedTime":"2011-08-30T18:09:55.000+0000","mediaLink":null,"mediaIcon":null,"attributes":{"provides":{"noApp":false,"dockMode":false,"universalSearch":false,"connectors":["null"],"services":[],"optimizedUserExperience":true}},"price":0,"currency":"USD","isAdvertized":false,"filename":"com.doublesix.app.babe_1.0.1_all.ipk","free":false,"touchpad_exclusive":true,"images":{"1":{"thumbnail":"10313\/1.0.1\/en\/images\/1\/S\/ph_mzl.igamqnkd.320x480-75.jpg","screenshot":"10313\/1.0.1\/en\/images\/1\/L\/ph_mzl.igamqnkd.320x480-75.jpg","orientation":"L","device":"P"},"2":{"thumbnail":"10313\/1.0.1\/en\/images\/2\/S\/ph_mzl.nnuhqdwj.320x480-75.jpg","screenshot":"10313\/1.0.1\/en\/images\/2\/L\/ph_mzl.nnuhqdwj.320x480-75.jpg","orientation":"L","device":"P"},"3":{"thumbnail":"10313\/1.0.1\/en\/images\/3\/S\/ph_mzl.qgiwjicj.320x480-75.jpg","screenshot":"10313\/1.0.1\/en\/images\/3\/L\/ph_mzl.qgiwjicj.320x480-75.jpg","orientation":"L","device":"P"},"4":{"thumbnail":"10313\/1.0.1\/en\/images\/4\/S\/ph_mzl.tzsxxynu.320x480-75.jpg","screenshot":"10313\/1.0.1\/en\/images\/4\/L\/ph_mzl.tzsxxynu.320x480-75.jpg","orientation":"L","device":"P"},"5":{"thumbnail":"10313\/1.0.1\/en\/images\/5\/S\/ph_mzl.voulbjfg.320x480-75.jpg","screenshot":"10313\/1.0.1\/en\/images\/5\/L\/ph_mzl.voulbjfg.320x480-75.jpg","orientation":"L","device":"P"}}}