{"publicApplicationId":"com.dijit.lovebugsbackgrounds","description":"Love Bugs Backgrounds features cute heart-themed characters in a wide range sweet and funny situations.","version":"2.1.1","versionNote":"","homeURL":"http:\/\/www.dijit.com","supportURL":"http:\/\/www.dijit.com\/contact-dijit.aspx","custsupportemail":"support@dijit.com","custsupportphonenum":"877.547.2711","copyright":"copyright 2009 Dijit","licenseURL":"","locale":"en_US","appSize":1509844,"installSize":3768120,"isEncrypted":false,"adultRating":false,"islocationbased":false,"lastModifiedTime":"2010-01-07T00:34:51.000+0000","mediaLink":null,"mediaIcon":null,"attributes":{"provides":{"noApp":false,"dockMode":false,"universalSearch":false,"connectors":[],"services":[],"optimizedUserExperience":false}},"price":0.99,"currency":"USD","isAdvertized":false,"filename":"com.dijit.lovebugsbackgrounds_2.1.1_all.ipk","free":false,"touchpad_exclusive":false,"images":{"1":{"thumbnail":"1080\/en\/images\/1\/S\/lovebug1.png","screenshot":"1080\/en\/images\/1\/L\/lovebug1.png","orientation":"P","device":"P"},"2":{"thumbnail":"1080\/en\/images\/2\/S\/lovebug2.png","screenshot":"1080\/en\/images\/2\/L\/lovebug2.png","orientation":"P","device":"P"},"3":{"thumbnail":"1080\/en\/images\/3\/S\/lovebug3.png","screenshot":"1080\/en\/images\/3\/L\/lovebug3.png","orientation":"P","device":"P"}}}