{"publicApplicationId":"com.trileet.newsroom","description":"NewsRoom lets you keep up with all the latest news, right from your phone. With its dynamic interface and exclusive back end, NewsRoom is the fastest and most intuitive way to stay in touch while on the go. Instantly follow your favorite news, gadget, gossip, sports and fan sites, even when you don't have a signal. Fully supporting any RSS feed, it is perfect for both casual and expert users, no matter what the interest. With NewsRoom, you'll always be the first to know. \n\nNew in version 1.5.1\n* Fix e-mail sharing link broken in 1.5.0\nNew in version 1.5.0\n* Local and remote backup\n* Backup restore\n* Better handling of corrupt database\n* Various bug fixes\nNew in version 1.4.3\n* Better offline handling\n* Update fix\nNew in version 1.4.1\n* Clear Unread on Orange Click menu\n* Update fix\nNew in version 1.4.0\n* Preferences to control unread behavior.\n* Swipe up to view all unread articles.\n* Swipe down to clear unread articles.\n* Articles can now be starred.\n* Youtube views played through Youtube App\nNew in version 1.2.1\n* Feed list screen now resizes when there are pending notifications\n* Only background updates occur for feeds with notifications enabled for better battery performance.\n* Faster content updates with new server callback.\nNew in version 1.2.0\n* Big changes under the hood for performance improvements as well has reducing the memory used by the app significantly.\n* As promised, the 9 feed limit is gone. You can now add up to four pages for a total of 36.\n* Per-feed notifications. Tap a site while holding the orange key or visit the Site Manager to enable notifications for the sites you care about the most. NewsRoom will also keep things up to date for you even when you don't leave it open.\n* Article skim view now resizes when there are pending notifications.\n* Tap-hold on the site icons to rearrange them in the order of your liking.\n* Sites can now be renamed.","version":"1.5.1","versionNote":"","homeURL":"http:\/\/trileet.com","supportURL":"http:\/\/getsatisfaction.com\/trileet","custsupportemail":"newsroom@trileet.com","custsupportphonenum":"2064389244","copyright":"Copyright 2009-2010 Trileet, Inc.","licenseURL":"","locale":"en_US","appSize":479910,"installSize":4358144,"isEncrypted":false,"adultRating":false,"islocationbased":false,"lastModifiedTime":"2012-06-01T08:49:55.000+0000","mediaLink":null,"mediaIcon":null,"attributes":{"provides":{"noApp":false,"dockMode":false,"universalSearch":false,"connectors":["null"],"services":[],"optimizedUserExperience":false}},"price":4.99,"currency":"USD","isAdvertized":false,"filename":"com.trileet.newsroom_1.5.1_all.ipk","free":false,"touchpad_exclusive":false,"images":{"1":{"screenshot":"131\/1.5.1\/en\/images\/1\/L\/newsroom_1.png","thumbnail":"131\/1.5.1\/en\/images\/1\/L\/newsroom_1.png","orientation":"P","device":"P"},"2":{"screenshot":"131\/1.5.1\/en\/images\/2\/L\/newsroom_2.png","thumbnail":"131\/1.5.1\/en\/images\/2\/L\/newsroom_2.png","orientation":"P","device":"P"},"3":{"screenshot":"131\/1.5.1\/en\/images\/3\/L\/newsroom_3.png","thumbnail":"131\/1.5.1\/en\/images\/3\/L\/newsroom_3.png","orientation":"P","device":"P"}}}