{"publicApplicationId":"com.mystuff.ccb","description":"ClearCheckbook is an application that lets you manage your finances directly from your WebOS device. Check out your balances, add transactions, manage your accounts and spending categories, view your accounts, reports, budgets, manage reminders and recurring transactions and more! ClearCheckbook integrates with the website ClearCheckbook.com, giving you the ability to manage your finances from anywhere you have an internet connection. ClearCheckbook.com is a free website that lets you manage your finances by providing tools for budgeting, reporting, balancing your checkbook, projecting future balances and more.  *Latest Update: Ability to add Split Transactions!","version":"1.2.11","versionNote":"Fixed some login issues and updated the app to work better with the new budgeting features.","homeURL":"http:\/\/www.clearcheckbook.com","supportURL":"http:\/\/www.clearcheckbook.com","custsupportemail":"contact@clearcheckbook.com","custsupportphonenum":"","copyright":"Copyright 2012 ClearCheckbook.com","licenseURL":"","locale":"en_US","appSize":68158,"installSize":3211264,"isEncrypted":false,"adultRating":false,"islocationbased":false,"lastModifiedTime":"2012-12-03T22:02:28.000+0000","mediaLink":"http:\/\/www.youtube.com\/watch?v=Zg-qqOZLiM0","mediaIcon":"http:\/\/img.youtube.com\/vi\/Zg-qqOZLiM0\/2.jpg","attributes":{"provides":{"noApp":false,"dockMode":false,"universalSearch":false,"connectors":["null"],"services":[],"optimizedUserExperience":false}},"price":0,"currency":"USD","isAdvertized":false,"filename":"com.mystuff.ccb_1.2.11_all.ipk","free":false,"touchpad_exclusive":false,"images":{"1":{"screenshot":"com.mystuff.ccb\/1.2.11\/en\/images\/1\/L\/320x480_320x480_ph_palm_ss1.png","thumbnail":"com.mystuff.ccb\/1.2.11\/en\/images\/1\/S\/320x480_75x112_ph_palm_ss1.png","orientation":"P","device":"P"},"2":{"screenshot":"com.mystuff.ccb\/1.2.11\/en\/images\/2\/L\/320x480_320x480_ph_palm_ss2.png","thumbnail":"com.mystuff.ccb\/1.2.11\/en\/images\/2\/S\/320x480_75x112_ph_palm_ss2.png","orientation":"P","device":"P"},"3":{"screenshot":"com.mystuff.ccb\/1.2.11\/en\/images\/3\/L\/320x480_320x480_ph_palm_ss3.png","thumbnail":"com.mystuff.ccb\/1.2.11\/en\/images\/3\/S\/320x480_75x112_ph_palm_ss3.png","orientation":"P","device":"P"},"4":{"screenshot":"com.mystuff.ccb\/1.2.11\/en\/images\/4\/L\/320x480_320x480_ph_palm_ss4.png","thumbnail":"com.mystuff.ccb\/1.2.11\/en\/images\/4\/S\/320x480_75x112_ph_palm_ss4.png","orientation":"P","device":"P"},"5":{"screenshot":"com.mystuff.ccb\/1.2.11\/en\/images\/5\/L\/320x480_320x480_ph_palm_ss5.png","thumbnail":"com.mystuff.ccb\/1.2.11\/en\/images\/5\/S\/320x480_75x112_ph_palm_ss5.png","orientation":"P","device":"P"}}}