{"publicApplicationId":"com.doin.memorygamefree","description":"This game is made so that you can improve you memory skills just look at the pieces on the device and try to remember them when you're asked again, you'll improve you brain capacity with fun","version":"1.0.5","versionNote":"","homeURL":"http:\/\/doiim.com","supportURL":"http:\/\/doiim.com\/","custsupportemail":"contact@doiim.com","custsupportphonenum":"554333715812","copyright":"Copyright 2011 Doiim, Inc.","licenseURL":"","locale":"en_US","appSize":425634,"installSize":1966080,"isEncrypted":false,"adultRating":false,"islocationbased":false,"lastModifiedTime":"2011-04-13T18:30:28.000+0000","mediaLink":null,"mediaIcon":null,"attributes":{"provides":{"noApp":false,"dockMode":false,"universalSearch":false,"connectors":[],"services":[],"optimizedUserExperience":false}},"price":0,"currency":"USD","isAdvertized":false,"filename":"com.doin.memorygamefree_1.0.5_all.ipk","free":false,"touchpad_exclusive":false,"images":{"1":{"thumbnail":"1656\/en\/images\/1\/S\/Picture.png","screenshot":"1656\/en\/images\/1\/L\/Picture.png","orientation":"P","device":"P"},"2":{"thumbnail":"1656\/en\/images\/2\/S\/Picture2.png","screenshot":"1656\/en\/images\/2\/L\/Picture2.png","orientation":"P","device":"P"}}}