{"publicApplicationId":"com.bowdenapps.guitartabsearch","description":"Guitar Tab Search. Search for your favorite song tabs right from your pre or pixi.  Search from four different tab sources and get your tabs right on your phone.  Search by song or artist quick and easy no need to go find the nearest computer.(Update removes need for external browser)","version":"1.3.1","versionNote":"","homeURL":"http:\/\/www.bowdenapps.com","supportURL":"http:\/\/www.bowdenapps.com","custsupportemail":"support@bowdenapps.com","custsupportphonenum":"","copyright":"Copyright 2010 Bowden Apps","licenseURL":"","locale":"en_US","appSize":370106,"installSize":2485503,"isEncrypted":false,"adultRating":false,"islocationbased":false,"lastModifiedTime":"2012-06-01T04:55:34.000+0000","mediaLink":null,"mediaIcon":null,"attributes":{"provides":{"noApp":false,"dockMode":false,"universalSearch":false,"connectors":["null"],"services":[],"optimizedUserExperience":false}},"price":1.25,"currency":"USD","isAdvertized":false,"filename":"com.bowdenapps.guitartabsearch_1.3.1_all.ipk","free":false,"touchpad_exclusive":false,"images":{"1":{"screenshot":"1730\/1.3.1\/en\/images\/1\/L\/guitartabsearch_2010-18-07_133637.png","thumbnail":"1730\/1.3.1\/en\/images\/1\/L\/guitartabsearch_2010-18-07_133637.png","orientation":"P","device":"P"},"2":{"screenshot":"1730\/1.3.1\/en\/images\/2\/L\/guitartabsearch_2010-18-07_133649.png","thumbnail":"1730\/1.3.1\/en\/images\/2\/L\/guitartabsearch_2010-18-07_133649.png","orientation":"P","device":"P"},"3":{"screenshot":"1730\/1.3.1\/en\/images\/3\/L\/guitartabsearch_2010-18-07_133700.png","thumbnail":"1730\/1.3.1\/en\/images\/3\/L\/guitartabsearch_2010-18-07_133700.png","orientation":"P","device":"P"}}}