{"publicApplicationId":"com.jaf0.bestprice","description":">>Update<<\nNow AD Free. Donate if you find it useful.\n\nRecent Features are currently in English only & will be localized eventually. \nThis application is a cost per unit calculator designed to save you money. It simplifies obtaining and comparing the unit cost of an item in four different quantities and provides detailed result information. It contains built-in unit conversion between common measurements in liquid, weight, and length.\nOnce you get the results, you can share them via email, SMS, or instant messaging! There is also a multiple percent discount calculator (work in progress) which has been updated to include sales tax if you wish. \nAlso, based on feedback from the catalog, I have included the option to force English. \nIf there are further improvements you wish to see (either in the program or the language translation) please leave feedback or contact me! \n\nYou can easily find the best value while doing your shopping. \n* Update: Metrix and UI Tweaks.\n* Update: added area conversions. \n* Minor bug fixes, UI tweaks and update notification (via puchk).","version":"1.0.0","versionNote":"","homeURL":"http:\/\/www.jaf0.com","supportURL":"http:\/\/bit.ly\/jaf0support","custsupportemail":"jaf0.sdr@gmail.com","custsupportphonenum":"","copyright":"Copyright 2009-2011 Daniel Weigh","licenseURL":"","locale":"en_US","appSize":119342,"installSize":3440640,"isEncrypted":false,"adultRating":false,"islocationbased":false,"lastModifiedTime":"2011-09-28T19:42:45.000+0000","mediaLink":null,"mediaIcon":null,"attributes":{"provides":{"noApp":false,"dockMode":false,"universalSearch":false,"connectors":["null"],"services":[],"optimizedUserExperience":false}},"price":0,"currency":"USD","isAdvertized":false,"filename":"com.jaf0.bestprice_1.0.0_all.ipk","free":false,"touchpad_exclusive":false,"images":{"1":{"screenshot":"1885\/1.0.0\/en\/images\/1\/L\/ph_bestprice_2011-26-09_192805.png","thumbnail":"1885\/1.0.0\/en\/images\/1\/S\/ph_bestprice_2011-26-09_192805.png","orientation":"P","device":"P"},"2":{"screenshot":"1885\/1.0.0\/en\/images\/2\/L\/ph_bestprice_2011-26-09_192810.png","thumbnail":"1885\/1.0.0\/en\/images\/2\/S\/ph_bestprice_2011-26-09_192810.png","orientation":"P","device":"P"},"3":{"screenshot":"1885\/1.0.0\/en\/images\/3\/L\/ph_bestprice_2011-26-09_192820.png","thumbnail":"1885\/1.0.0\/en\/images\/3\/S\/ph_bestprice_2011-26-09_192820.png","orientation":"P","device":"P"}}}