{"publicApplicationId":"com.thirdwishsoftware.timecodecalc","description":"Simple Timecode calculator with conversion between number of frames and 24, 25, 30, 50 and 60 frames per second timecodes, drop and non-drop frame. Thanks to all who reported issues, please let me know if you find anything else that is not right or if you have suggestions to make this app better!","version":"1.0.6","versionNote":"","homeURL":"http:\/\/thirdwishsoftware.com\/timecodecalculator","supportURL":"http:\/\/thirdwishsoftware.com\/timecodecalculator","custsupportemail":"support@thirdwishsoftware.com","custsupportphonenum":"","copyright":"Copyright 2010 Third Wish Software","licenseURL":"","locale":"en_US","appSize":80598,"installSize":1510952,"isEncrypted":false,"adultRating":false,"islocationbased":false,"lastModifiedTime":"2011-06-29T06:18:02.000+0000","mediaLink":null,"mediaIcon":null,"attributes":{"provides":{"noApp":false,"dockMode":false,"universalSearch":false,"connectors":[],"services":[],"optimizedUserExperience":false}},"price":0,"currency":"USD","isAdvertized":false,"filename":"com.thirdwishsoftware.timecodecalc_1.0.6_all.ipk","free":false,"touchpad_exclusive":false,"images":{"1":{"thumbnail":"3146\/en\/images\/1\/S\/ph_timecodecalculator1.png","screenshot":"3146\/en\/images\/1\/L\/ph_timecodecalculator1.png","orientation":"P","device":"P"},"2":{"thumbnail":"3146\/en\/images\/2\/S\/ph_timecodecalculator2.png","screenshot":"3146\/en\/images\/2\/L\/ph_timecodecalculator2.png","orientation":"P","device":"P"},"3":{"thumbnail":"3146\/en\/images\/3\/S\/ph_timecodecalculator3.png","screenshot":"3146\/en\/images\/3\/L\/ph_timecodecalculator3.png","orientation":"P","device":"P"}}}