{"publicApplicationId":"com.ingloriousapps.flickrcam","description":"Seamlessly upload pictures from your phone to your Flickr account with just one button. Launching the app launches the camera instantly, and you can just begin snapping pictures. The pictures are then automatically uploaded in the background. You can also choose to manually select pictures from your phone to upload.\n\nNew in Version 1.0.2\n- Added Ability to set default upload folder in preference\n\nIf you have any questions, issues or suggestions, send a direct email to ingloriousapps@gmail.com. Check out other Inglorious Apps: Notes, Voices, Casa, Plickr, Crushed, Bouncey & MediaVault","version":"1.0.2","versionNote":"Added Ability to set default upload folder in preference","homeURL":"http:\/\/www.ingloriousapps.com","supportURL":"http:\/\/www.ingloriousapps.com","custsupportemail":"ingloriousapps@gmail.com","custsupportphonenum":"","copyright":"copyright","licenseURL":"","locale":"en_US","appSize":269336,"installSize":9469952,"isEncrypted":false,"adultRating":false,"islocationbased":false,"lastModifiedTime":"2012-06-01T19:03:57.000+0000","mediaLink":"http:\/\/www.youtube.com\/watch?v=gvgh6tY4iy4","mediaIcon":"http:\/\/img.youtube.com\/vi\/gvgh6tY4iy4\/2.jpg","attributes":{"provides":{"noApp":false,"dockMode":false,"universalSearch":false,"connectors":["null"],"services":[],"optimizedUserExperience":false}},"price":0.99,"currency":"USD","isAdvertized":false,"filename":"com.ingloriousapps.flickrcam_1.0.2_all.ipk","free":false,"touchpad_exclusive":false,"images":{"1":{"screenshot":"3331\/1.0.2\/en\/images\/1\/L\/flickrcam1.png","thumbnail":"3331\/1.0.2\/en\/images\/1\/L\/flickrcam1.png","orientation":"P","device":"P"},"2":{"screenshot":"3331\/1.0.2\/en\/images\/2\/L\/flickrcam2.png","thumbnail":"3331\/1.0.2\/en\/images\/2\/L\/flickrcam2.png","orientation":"P","device":"P"},"3":{"screenshot":"3331\/1.0.2\/en\/images\/3\/L\/flickrcam3.png","thumbnail":"3331\/1.0.2\/en\/images\/3\/L\/flickrcam3.png","orientation":"P","device":"P"}}}