{"publicApplicationId":"com.dblpartners.sofwaretestingcast","description":"This app for the palm webOS contains 263 professionally written flash cards to hone your knowledge for the Certified Associate in Software Testing (CAST) certification exam.  *   Each flash card contains a key term or concept from the QAI CAST Common Body of Knowledge (CBOK), followed by a clear and concise explanation and definition.  ||  All of our app content is created exclusively for Upward Mobility by expert writers who have strong knowledge in the subject matter and all of our materials undergo a thorough review process.  ||  Our flash card app has simple, intuitive navigation, with the ability to shuffle cards, to remove flash cards from the deck, and to reset the deck.  *  Vocabulary Topics include Software Testing Principles and Concepts, the Test Environment, Test Planning and execution, Test Status, Analysis and Reporting, User Acceptance planning  ||  This app is the ideal on-the-go study aid for the busy IT professional!  ||  Upward Mobility creates high quality management education and test preparation material that is witty, engaging, and adds value in the learning process.  *   We are a double bottom line company committed to education in the developing world. Some of the profits will be used to deploy education via mobile phone in emerging countries.","version":"1.0.0","versionNote":"","homeURL":"http:\/\/upwardpro.com","supportURL":"http:\/\/upwardpro.com","custsupportemail":"info@upwardpro.com","custsupportphonenum":"","copyright":"DBL Partners LLC","licenseURL":"","locale":"en_US","appSize":336834,"installSize":2722751,"isEncrypted":false,"adultRating":false,"islocationbased":false,"lastModifiedTime":"2012-06-01T06:01:36.000+0000","mediaLink":null,"mediaIcon":null,"attributes":{"provides":{"noApp":false,"dockMode":false,"universalSearch":false,"connectors":["null"],"services":[],"optimizedUserExperience":false}},"price":2.99,"currency":"USD","isAdvertized":false,"filename":"com.dblpartners.sofwaretestingcast_1.0.0_all.ipk","free":false,"touchpad_exclusive":false,"images":{"1":{"screenshot":"4497\/1.0.0\/en\/images\/1\/L\/1.png","thumbnail":"4497\/1.0.0\/en\/images\/1\/L\/1.png","orientation":"P","device":"P"},"2":{"screenshot":"4497\/1.0.0\/en\/images\/2\/L\/2.png","thumbnail":"4497\/1.0.0\/en\/images\/2\/L\/2.png","orientation":"P","device":"P"},"3":{"screenshot":"4497\/1.0.0\/en\/images\/3\/L\/3.png","thumbnail":"4497\/1.0.0\/en\/images\/3\/L\/3.png","orientation":"P","device":"P"},"4":{"screenshot":"4497\/1.0.0\/en\/images\/4\/L\/4.png","thumbnail":"4497\/1.0.0\/en\/images\/4\/L\/4.png","orientation":"P","device":"P"},"5":{"screenshot":"4497\/1.0.0\/en\/images\/5\/L\/5.png","thumbnail":"4497\/1.0.0\/en\/images\/5\/L\/5.png","orientation":"P","device":"P"}}}