{"publicApplicationId":"com.dirs.pmirror","description":"pMirror is a simple application that simulates a mirror it's a black screen with a mirror frame around it so  you can see yourself in the reflection of the screen","version":"1.1.0","versionNote":"","homeURL":"http:\/\/pomoti.com\/file\/doin","supportURL":"http:\/\/pomoti.com\/file\/pmirror","custsupportemail":"gabriel.oliveira.m@gmail.com","custsupportphonenum":"..","copyright":"Copyright 2009 Doin, Inc.","licenseURL":"","locale":"en_US","appSize":364946,"installSize":1086741,"isEncrypted":false,"adultRating":false,"islocationbased":false,"lastModifiedTime":"2010-01-12T00:52:44.000+0000","mediaLink":null,"mediaIcon":null,"attributes":{"provides":{"noApp":false,"dockMode":false,"universalSearch":false,"connectors":[],"services":[],"optimizedUserExperience":false}},"price":0,"currency":"USD","isAdvertized":false,"filename":"com.dirs.pmirror_1.1.0_all.ipk","free":false,"touchpad_exclusive":false,"images":{"1":{"thumbnail":"488\/en\/images\/1\/S\/Screenshot.png","screenshot":"488\/en\/images\/1\/L\/Screenshot.png","orientation":"P","device":"P"}}}