{"publicApplicationId":"com.appible.representativemenaudio","description":"In this app you can download & store chapters for listening without an internet connection, perhaps on your next flight or road trip. These audiobooks are great for your commute, long trips, hours at the gym or to just listen while washing the dishes.\n\nA series of biographical lectures originally published in 1850. Each chapter is a philosophical treatment of the life of an intellectual. The six representatives are Plato, Swedenborg, Shakespeare, Montaigne, Napolean and Goethe. (Introduction by S. Kovalchik)\n\nThis audiobook uses recordings from Librivox.org, a community of generous volunteers who record public domain works and then publish their recordings in the public domain. The app is based on drPodder which was graciously provided to the open source community by drnull.","version":"1.0.0","homeURL":"http:\/\/appible.com\/contact","supportURL":"http:\/\/appible.com\/contact","custsupportemail":"","custsupportphonenum":"","copyright":"Copyright 2010 Appible LLC","licenseURL":"http:\/\/appible.com\/contact","locale":null,"appSize":"288578","installSize":"288578","isEncrypted":null,"adultRating":null,"islocationbased":null,"lastModifiedTime":null,"mediaLink":null,"mediaIcon":null,"attributes":[],"price":"1.2","currency":"USD","filename":"com.appible.representativemenaudio_1.0.0_all.ipk","free":false,"images":[{"thumbnail":"7101\/images\/1\/L\/representativemen1.png","screenshot":"7101\/images\/1\/L\/representativemen1.png","orientation":"P","device":"P"},{"thumbnail":"7101\/images\/2\/L\/representativemen2.png","screenshot":"7101\/images\/2\/L\/representativemen2.png","orientation":"P","device":"P"}]}