{"publicApplicationId":"com.handmark.mpp.nydn","description":"No other city is quite like New York and the Daily News is the number one paper for coverage of what goes on \u2013 from the politics to the gossip. And when it comes to Sports, our writers know the Yankees, Mets, Giants and Jets better than any \u2013 its why year after year we win awards for the best Sports coverage.\nGet complete coverage on our simple, fast and easy-to-use app.","version":"2.0700.25057","versionNote":"","homeURL":"http:\/\/www.handmark.com","supportURL":"http:\/\/www.handmark.com\/support","custsupportemail":"","custsupportphonenum":"","copyright":"copyright 2011, NYDN; Handmark, Inc.","licenseURL":"","locale":"en_US","appSize":254644,"installSize":7110656,"isEncrypted":false,"adultRating":false,"islocationbased":false,"lastModifiedTime":"2011-04-06T07:48:24.000+0000","mediaLink":null,"mediaIcon":null,"attributes":{"provides":{"noApp":false,"dockMode":false,"universalSearch":false,"connectors":[],"services":[],"optimizedUserExperience":false}},"price":0,"currency":"USD","isAdvertized":false,"filename":"com.handmark.mpp.nydn_2.0700.25057_all.ipk","free":false,"touchpad_exclusive":false,"images":{"1":{"thumbnail":"8357\/en\/images\/1\/S\/wos_ss_1.jpg","screenshot":"8357\/en\/images\/1\/L\/wos_ss_1.jpg","orientation":"P","device":"P"},"2":{"thumbnail":"8357\/en\/images\/2\/S\/wos_ss_2.jpg","screenshot":"8357\/en\/images\/2\/L\/wos_ss_2.jpg","orientation":"P","device":"P"},"3":{"thumbnail":"8357\/en\/images\/3\/S\/wos_ss_3.jpg","screenshot":"8357\/en\/images\/3\/L\/wos_ss_3.jpg","orientation":"P","device":"P"},"4":{"thumbnail":"8357\/en\/images\/4\/S\/wos_ss_4.jpg","screenshot":"8357\/en\/images\/4\/L\/wos_ss_4.jpg","orientation":"P","device":"P"},"5":{"thumbnail":"8357\/en\/images\/5\/S\/wos_ss_5.jpg","screenshot":"8357\/en\/images\/5\/L\/wos_ss_5.jpg","orientation":"P","device":"P"}}}