{"publicApplicationId":"com.smarteragent.realestate.kbt","description":"The Koehler Bortnick Team Mobile App is ideal for the house hunter on the go! Instead of mapping out the homes you want to see from your computer, simply download this mobile app to see real-time information about homes for sale in your area of interest.  You can search by listing number, neighborhood, city, zip code, school district, address, or just let the GPS map guide you to your next dream home! \n\nYou will see a home\u2019s price, photos, description of the interior and exterior, and information on similar properties recently sold just to name a few.  You can refine your search by type of home, price range, number of bedrooms and bathrooms, and location.  \n\nThe app is free to use.  Let your home shopping adventure begin right from the palm of your hand!","version":"4.0.0","versionNote":"","homeURL":"http:\/\/www.smarteragent.com","supportURL":"http:\/\/www.smarteragent.com","custsupportemail":"palm@smarteragent.com","custsupportphonenum":"","copyright":"2010 Smarter Agent Inc.","licenseURL":"","locale":"en_US","appSize":241148,"installSize":5668864,"isEncrypted":false,"adultRating":false,"islocationbased":true,"lastModifiedTime":"2011-05-23T01:30:02.000+0000","mediaLink":null,"mediaIcon":null,"attributes":{"provides":{"noApp":false,"dockMode":false,"universalSearch":false,"connectors":[],"services":[],"optimizedUserExperience":false}},"price":0,"currency":"USD","isAdvertized":false,"filename":"com.smarteragent.realestate.kbt_4.0.0_all.ipk","free":false,"touchpad_exclusive":false,"images":{"1":{"thumbnail":"9010\/en\/images\/1\/S\/kbt_2011-06-05_093323.png","screenshot":"9010\/en\/images\/1\/L\/kbt_2011-06-05_093323.png","orientation":"P","device":"P"},"2":{"thumbnail":"9010\/en\/images\/2\/S\/kbt_2011-06-05_093600.png","screenshot":"9010\/en\/images\/2\/L\/kbt_2011-06-05_093600.png","orientation":"P","device":"P"},"3":{"thumbnail":"9010\/en\/images\/3\/S\/kbt_2011-06-05_093631.png","screenshot":"9010\/en\/images\/3\/L\/kbt_2011-06-05_093631.png","orientation":"P","device":"P"},"4":{"thumbnail":"9010\/en\/images\/4\/S\/kbt_2011-06-05_093700.png","screenshot":"9010\/en\/images\/4\/L\/kbt_2011-06-05_093700.png","orientation":"P","device":"P"},"5":{"thumbnail":"9010\/en\/images\/5\/S\/kbt_2011-06-05_093844.png","screenshot":"9010\/en\/images\/5\/L\/kbt_2011-06-05_093844.png","orientation":"P","device":"P"}}}