{"publicApplicationId":"com.openmerchantaccount.astronomy","description":"Wanted to know where to see Mars, Jupiter or Saturn in the night sky? Want to find more information about a star, galaxy, planet, satellite or moon? This is the app for you.","version":"1.0.0","versionNote":"","homeURL":"http:\/\/www.openmerchantaccount.com","supportURL":"http:\/\/www.openmerchantaccount.com","custsupportemail":"support@openmerchantaccount.com","custsupportphonenum":"","copyright":"Copyright 2011 Open Merchant Account Ltd.","licenseURL":"","locale":"en_US","appSize":251556,"installSize":3112960,"isEncrypted":false,"adultRating":false,"islocationbased":false,"lastModifiedTime":"2012-06-01T22:33:51.000+0000","mediaLink":null,"mediaIcon":null,"attributes":{"provides":{"noApp":false,"dockMode":false,"universalSearch":false,"connectors":["null"],"services":[],"optimizedUserExperience":false}},"price":1.99,"currency":"USD","isAdvertized":false,"filename":"com.openmerchantaccount.astronomy_1.0.0_all.ipk","free":false,"touchpad_exclusive":false,"images":[]}