{"publicApplicationId":"com.lastminute.theticketapp.production","description":"Sameday theatre tickets on the go. Its simple and fast to buy tickets using your HP for a great range of west end musicals and theatre performances. [English only]\n\nYou can check out the latest shows available today. you can see the latest ticket availability in real-time and pick the time of show that suits you best.\n\nOnce you have picked a show you can read detailed show info and reviews, find the best transport options and see the theatres on your mobile map application.\n\nJust call our UK call centre to choose seats and make payment with a credit card. You can book tickets until the very last-minute before the show, just make sure you can get to the theatre in time!\n\nOnce you have paid you will be emailed your reservation and you can pick up your tickets at the theatre box office before the show by giving your name and having the credit card you purchased with as proof of purchase, simple!","version":"1.0.252","versionNote":"","homeURL":"http:\/\/www.lastminute.com","supportURL":"http:\/\/www.lastminute.com","custsupportemail":"","custsupportphonenum":"","copyright":"copyright 2011 lastminute network ltd","licenseURL":"","locale":"en_US","appSize":1872628,"installSize":4849664,"isEncrypted":false,"adultRating":false,"islocationbased":true,"lastModifiedTime":"2011-07-15T05:28:22.000+0000","mediaLink":null,"mediaIcon":null,"attributes":{"provides":{"noApp":false,"dockMode":false,"universalSearch":false,"connectors":[],"services":[],"optimizedUserExperience":false}},"price":0,"currency":"USD","isAdvertized":false,"filename":"com.lastminute.theticketapp.production_1.0.252_all.ipk","free":false,"touchpad_exclusive":true,"images":{"1":{"thumbnail":"9747\/en\/images\/1\/S\/conv_tb_TheTicketApp.png","screenshot":"9747\/en\/images\/1\/L\/conv_tb_TheTicketApp.png","orientation":"P","device":"P"},"2":{"thumbnail":"9747\/en\/images\/2\/S\/conv_tb_production_2011-04-07_151345.png","screenshot":"9747\/en\/images\/2\/L\/conv_tb_production_2011-04-07_151345.png","orientation":"P","device":"P"},"3":{"thumbnail":"9747\/en\/images\/3\/S\/conv_tb_production_2011-04-07_151350.png","screenshot":"9747\/en\/images\/3\/L\/conv_tb_production_2011-04-07_151350.png","orientation":"P","device":"P"},"4":{"thumbnail":"9747\/en\/images\/4\/S\/conv_tb_production_2011-04-07_151354.png","screenshot":"9747\/en\/images\/4\/L\/conv_tb_production_2011-04-07_151354.png","orientation":"P","device":"P"},"5":{"thumbnail":"9747\/en\/images\/5\/S\/tb_production_2011-04-07_151205.png","screenshot":"9747\/en\/images\/5\/L\/tb_production_2011-04-07_151205.png","orientation":"P","device":"P"}}}